keven_core/__init__.py
keven_core/configuration/__init__.py
keven_core/configuration/_main.py
keven_core/database/__init__.py
keven_core/exceptions/__init__.py
keven_core/exceptions/code.py
keven_core/exceptions/communications.py
keven_core/exceptions/database.py
keven_core/grpc/__init__.py
keven_core/grpc/grpc_service_metaclass.py
keven_core/kafka/README.md
keven_core/kafka/__init__.py
keven_core/kafka/abstracts/__init__.py
keven_core/kafka/abstracts/command_handler.py
keven_core/kafka/abstracts/command_handler_bkup.py
keven_core/kafka/abstracts/command_receiver.py
keven_core/kafka/abstracts/commandevent.py
keven_core/kafka/abstracts/consumer_server.py
keven_core/kafka/abstracts/delayed.py
keven_core/kafka/abstracts/event_handler.py
keven_core/kafka/abstracts/event_handler_bkup.py
keven_core/kafka/abstracts/eventreceiver_server.py
keven_core/kafka/abstracts/message.py
keven_core/kafka/abstracts/message_publisher.py
keven_core/kafka/abstracts/message_server.py
keven_core/kafka/abstracts/metaclass/__init__.py
keven_core/kafka/abstracts/metaclass/base_handler_meta.py
keven_core/kafka/abstracts/metaclass/base_registry.py
keven_core/kafka/abstracts/metaclass/handler_meta.py
keven_core/kafka/commands/__init__.py
keven_core/kafka/commands/command.py
keven_core/kafka/commands/command_names.py
keven_core/kafka/commands/command_server.py
keven_core/kafka/commands/dispatcher.py
keven_core/kafka/commands/publisher.py
keven_core/kafka/commands/runner.py
keven_core/kafka/commands/test/__init__.py
keven_core/kafka/commands/test/test.py
keven_core/kafka/commands/test/test_command_pb2.py
keven_core/kafka/events/__init__.py
keven_core/kafka/events/event.py
keven_core/kafka/events/event_names.py
keven_core/kafka/events/logger.py
keven_core/kafka/events/publisher.py
keven_core/kafka/events/runner.py
keven_core/kafka/events/server.py
keven_core/kafka/logger.py
keven_core/kafka/tests/__init__.py
keven_core/kafka/tests/conftest.py
keven_core/kafka/tests/test_command_handler.py
keven_core-1.0.0.dist-info/METADATA
keven_core-1.0.0.dist-info/WHEEL
keven_core-1.0.0.dist-info/RECORD
