Metadata-Version: 2.3
Name: keven_core
Version: 1.0.0
Summary: Core utilities and shared components for KEVEN's microservices.
License: AGPL-3.0
Author: Craig Holland
Author-email: craig_holland@hotmail.com
Requires-Python: >=3.12,<4.0
Classifier: License :: OSI Approved :: GNU Affero General Public License v3
Classifier: Programming Language :: Python :: 3
Classifier: Programming Language :: Python :: 3.12
Classifier: Programming Language :: Python :: 3.13
Requires-Dist: PyJWT (>=2.6.0,<3.0.0)
Requires-Dist: aenum (>=3.1.15,<4.0.0)
Requires-Dist: confluent-kafka (>=2.8.2,<3.0.0)
Requires-Dist: grpcio (==1.71.0)
Requires-Dist: grpcio-tools (==1.71.0)
Requires-Dist: jsonpickle (>=4.0.2,<5.0.0)
Requires-Dist: kafka-python (>=2.0.2,<3.0.0)
Requires-Dist: loguru (>=0.7.0,<0.8.0)
Requires-Dist: protobuf (>=5.26.1,<6.0)
Requires-Dist: psycopg2-binary (>=2.9.6,<3.0.0)
Requires-Dist: pydantic (>=2.0,<3.0)
Requires-Dist: pydantic-settings (>=2.8.1,<3.0.0)
Requires-Dist: python-dotenv (>=1.0.1,<2.0.0)
Requires-Dist: sqlalchemy (>=2.0.0,<3.0.0)
Requires-Dist: types-requests (>=2.28.11,<3.0.0)
